{
  "hiddenCommands": [
    "cmd_maximizeWindow",
    "cmd_minimizeWindow",
    "Browser:OpenFile",
    "sine:install:browse-bot",
    "sine:install:floating-sidebar",
    "sine:install:reopen-closed-tabs",
    "sine:install:search-engine-select",
    "sine:install:settings-shortcuts-search",
    "sine:install:zen-command-palette",
    "sine:uninstall:No-Gaps",
    "sine:uninstall:642854b5-88b4-4c40-b256-e035532109df",
    "sine:uninstall:zen-custom-js"
  ],
  "customIcons": {},
  "customShortcuts": {
    "Browser:NextTab": "Alt+J",
    "Browser:PrevTab": "Alt+K",
    "app:clear-startupCache": "Ctrl+Alt+Shift+R",
    "app:minimize-memory": "Ctrl+Alt+Shift+M",
    "cmd_zenCompactModeShowSidebar": "Alt+S",
    "cmd_zenCompactModeShowToolbar": "Alt+T",
    "command-palette:settings-commands": "Ctrl+,",
    "command-palette:show": "Ctrl+Shift+P",
    "custom:advanced-settings": "Ctrl+Alt+Shift+S",
    "custom:close-and-next": "Ctrl+Alt+N",
    "custom:close-and-prev": "Ctrl+Alt+P",
    "custom:open-settings": "Ctrl+Alt+S",
    "custom:paste-and-go": "Alt+V",
    "custom:transparency": "Ctrl+Alt+Shift+T",
    "duplicate-tab": "Alt+D",
    "move-tab-down": "Ctrl+Alt+J",
    "move-tab-up": "Ctrl+Alt+K",
    "toggle-collapsed-pins": "Alt+P",
    "toggle-sidebar": "Ctrl+Alt+A",
    "toggle-toolbar": "Ctrl+Alt+T",
    "unload-other-tabs": "Ctrl+Alt+U",
    "unload-tab": "Alt+U",
    "browsebot:settings": "Alt+E"
  },
  "toolbarButtons": [],
  "customCommands": [
    {
      "type": "chain",
      "id": "advanced-settings",
      "name": "Open Advanced Settings",
      "commands": [
        {
          "action": "openLink",
          "params": {
            "link": "about:config",
            "where": "new tab"
          }
        },
        {
          "action": "showToast",
          "params": {
            "title": "Advanced settings opened",
            "description": "Be careful while changing settings"
          }
        }
      ],
      "icon": "chrome://browser/skin/zen-icons/settings.svg"
    },
    {
      "type": "chain",
      "id": "open-settings",
      "name": "Open Settings",
      "commands": [
        {
          "action": "openLink",
          "params": {
            "link": "about:preferences",
            "where": "new tab"
          }
        }
      ],
      "icon": "chrome://browser/skin/zen-icons/settings.svg"
    },
    {
      "type": "js",
      "id": "paste-and-go",
      "name": "Paste and go",
      "code": "navigator.clipboard.readText().then((text) => {\n  if (text) {\n    try {\n      new URL(text);\n      openTrustedLinkIn(text, \"tab\");\n    } catch (error) {\n      const searchURL = `https://duckduckgo.com/?q=${encodeURIComponent(text)}`;\n      openTrustedLinkIn(searchURL, \"tab\");\n    }\n  }\n});",
      "icon": "chrome://browser/skin/zen-icons/edit-paste.svg"
    },
    {
      "type": "js",
      "id": "close-and-prev",
      "name": "Close Tab and Go Previous",
      "code": "const tabToClose = gBrowser.selectedTab;\ngBrowser.tabContainer.advanceSelectedTab(-1, true);\ngBrowser.removeTab(tabToClose);",
      "icon": "chrome://browser/skin/zen-icons/arrow-up.svg"
    },
    {
      "type": "js",
      "id": "close-and-next",
      "name": "Close Tab and Go Next",
      "code": "const tabToClose = gBrowser.selectedTab;\ngBrowser.tabContainer.advanceSelectedTab(1, true);\ngBrowser.removeTab(tabToClose);",
      "icon": "chrome://browser/skin/zen-icons/arrow-down.svg"
    },
    {
      "type": "js",
      "id": "transparency",
      "name": "Toggle transparency",
      "code": "(async function() {\n  const browserTransparent = Services.prefs.getBoolPref(\n    \"browser.tabs.allow_transparent_browser\",\n  );\n\n  const prefs = [\n    \"browser.tabs.allow_transparent_browser\",\n    \"mod.sameerasw.zen_transparent_glance_enabled\",\n    \"widget.transparent-windows\",\n    \"zen.widget.linux.transparency\",\n  ];\n\n  for (let pref of prefs) {\n    Services.prefs.setBoolPref(pref, !browserTransparent);\n  }\n\n  const zenInternetId = \"{91aa3897-2634-4a8a-9092-279db23a7689}\";\n  const transparentZenId = \"642854b5-88b4-4c40-b256-e035532109df\";\n  const zenInternet = await AddonManager.getAddonByID(zenInternetId);\n\n  const utils = ChromeUtils.importESModule(\n    \"chrome://userscripts/content/engine/core/utils.mjs\",\n  ).default;\n  const installedMods = await utils.getMods();\n  const transparentZen = installedMods[transparentZenId];\n  if (transparentZen) {\n    if (\n      (browserTransparent && transparentZen.enabled) ||\n      (!browserTransparent && !transparentZen.enabled)\n    ) {\n      SineAPI.manager.toggleTheme(installedMods, transparentZenId);\n    }\n  }\n\n  if (browserTransparent) zenInternet?.disable();\n  else zenInternet?.enable();\n\n  try {\n    const showToast = ChromeUtils.importESModule(\n      \"chrome://sine/content/zen-custom-js/utils/toast.js\",\n    ).showToast;\n    showToast({\n      title: `Transparency ${browserTransparent ? \"Disabled\" : \"Enabled\"}`,\n      description: \"A restart is required for clhanges to take effect\",\n      preset: 1,\n    });\n  } catch {\n    //ignore\n  }\n})();\n",
      "icon": "chrome://browser/skin/trending.svg"
    }
  ]
}
